topsis/__init__.py
topsis/__main__.py
TOPSIS_JASHANDEEP_102218023-1.1.2.dist-info/LICENCE
TOPSIS_JASHANDEEP_102218023-1.1.2.dist-info/METADATA
TOPSIS_JASHANDEEP_102218023-1.1.2.dist-info/WHEEL
TOPSIS_JASHANDEEP_102218023-1.1.2.dist-info/entry_points.txt
TOPSIS_JASHANDEEP_102218023-1.1.2.dist-info/top_level.txt
TOPSIS_JASHANDEEP_102218023-1.1.2.dist-info/RECORD
