Metadata-Version: 2.1
Name: TOPSIS-JASHANDEEP-102218023
Version: 1.1.2
Summary: This Python package implements the Technique for Order of Preference by Similarity to Ideal Solution (TOPSIS) for multi-criteria decision-making.
Home-page: https://github.com/JASHANDEEPSINGH2608/TOPSIS-ML-project
Author: Jashandeep Singh
Author-email: jashandeepgarry2003@gmail.com
License: MIT
Classifier: License :: OSI Approved :: MIT License
Classifier: Programming Language :: Python :: 3.6
Classifier: Programming Language :: Python :: 3.7
Classifier: Programming Language :: Python :: 3.8
License-File: LICENCE
Requires-Dist: pandas
Requires-Dist: numpy
